nanoca.py
nanoca-0.10.data/scripts/nanoca
nanoca-0.10.dist-info/LICENSE.txt
nanoca-0.10.dist-info/METADATA
nanoca-0.10.dist-info/WHEEL
nanoca-0.10.dist-info/top_level.txt
nanoca-0.10.dist-info/RECORD
