Metadata-Version: 2.1
Name: nanoca
Version: 0.10
Summary: small library and cli tool for managing a certificate authority
Home-page: https://github.com/mo22/nanoca
Author: Moritz Möller
Author-email: mm@mxs.de
License: UNKNOWN
Platform: UNKNOWN
